[{"_path":"/dir/360factors","_dir":"dir","_draft":false,"_partial":false,"_locale":"","title":"360factors","description":"Delivering next-gen compliance management through AI-powered automation, insights, and predictive capabilities, this platform streamlines compliance while reducing costs for financial services.","featured":false,"card_image":"360factor-logo.png","_type":"markdown","_id":"content:dir:360factors.md","_source":"content","_file":"dir/360factors.md","_stem":"dir/360factors","_extension":"md","sitemap":{"loc":"/dir/360factors","images":[{"loc":"360factor-logo.png"}]}},{"_path":"/dir/appinventiv","_dir":"dir","_draft":false,"_partial":false,"_locale":"","title":"Appinventiv","description":"Specializing in innovative software development, this company empowers startups, enterprises, and public entities with cutting-edge solutions in compliance management, digital transformation, and customized cloud services across diverse industries.","featured":false,"card_image":"appi-blue-blk-logo.svg","_type":"markdown","_id":"content:dir:Appinventiv.md","_source":"content","_file":"dir/Appinventiv.md","_stem":"dir/Appinventiv","_extension":"md","sitemap":{"loc":"/dir/appinventiv","images":[{"loc":"appi-blue-blk-logo.svg"}]}}]